SqliteMQ/process_sql_queue.py
SqliteMQ/sql_queue.py
SqliteMQ/testcase/test.py
sqlitemq-0.1.dist-info/LICENSE
sqlitemq-0.1.dist-info/METADATA
sqlitemq-0.1.dist-info/WHEEL
sqlitemq-0.1.dist-info/top_level.txt
sqlitemq-0.1.dist-info/RECORD
