Metadata-Version: 2.2
Name: SqliteMQ
Version: 0.1
Summary: SqliteMQ is a simple Sqlite MQ server:Queue
Author-email: NelsonLongXiang <1169207670@qq.com>
Project-URL: Homepage, https://github.com/NelsonLongxiang/SqliteMQ
Project-URL: Issues, https://github.com/NelsonLongxiang/SqliteMQ/issues
Classifier: Programming Language :: Python :: 3
Classifier: License :: OSI Approved :: MIT License
Classifier: Operating System :: OS Independent
Requires-Python: >=3.9
License-File: LICENSE
